ztm/__init__.py
ztm/cli.py
ztm-0.1.12.dist-info/AUTHORS.rst
ztm-0.1.12.dist-info/LICENSE
ztm-0.1.12.dist-info/METADATA
ztm-0.1.12.dist-info/WHEEL
ztm-0.1.12.dist-info/entry_points.txt
ztm-0.1.12.dist-info/top_level.txt
ztm-0.1.12.dist-info/RECORD
