Metadata-Version: 2.1
Name: ztm
Version: 0.1.12
Summary: Fetch data from ZTM API
Home-page: https://github.com/wooyek/ztm
Author: Janusz Skonieczny
Author-email: js+pypi@bravelabs.pl
License: MIT license
Keywords: ztm
Platform: UNKNOWN
Classifier: Development Status :: 2 - Pre-Alpha
Classifier: Intended Audience :: Developers
Classifier: License :: OSI Approved :: MIT License
Classifier: Natural Language :: English
Classifier: Programming Language :: Python :: 3.4
Classifier: Programming Language :: Python :: 3.5
Classifier: Programming Language :: Python :: 3.6
Classifier: Programming Language :: Python :: 3.7
Requires-Python: >=3.4
Requires-Dist: backoff (==1.8.0)
Requires-Dist: certifi (==2018.11.29)
Requires-Dist: chardet (==3.0.4)
Requires-Dist: click (==7.0)
Requires-Dist: click-log (==0.3.2)
Requires-Dist: idna (==2.8)
Requires-Dist: ratelimit (==2.2.1)
Requires-Dist: requests (==2.21.0)
Requires-Dist: urllib3 (==1.24.1)
Provides-Extra: factories
Requires-Dist: factory-boy ; extra == 'factories'
